yid_py/__init__.py
yid_py/converter.py
youtube_id-1.0.3.dist-info/METADATA
youtube_id-1.0.3.dist-info/WHEEL
youtube_id-1.0.3.dist-info/licenses/LICENSE
youtube_id-1.0.3.dist-info/RECORD
