Metadata-Version: 2.4
Name: youtube-id
Version: 1.0.3
Summary: Generate YouTube-style short IDs from numbers. Lightweight, fast, and reversible base62 encoder with optional obfuscation.
License: MIT
License-File: LICENSE
Keywords: youtube-id,short-id,base62,hashid,url-shortener,id-generator,encoder,obfuscation,alphanumeric,unique-id
Author: Oleksii Samara
Author-email: oleksii@wildsoft.io
Requires-Python: >=3.10,<4.0
Classifier: Development Status :: 5 - Production/Stable
Classifier: Intended Audience :: Developers
Classifier: License :: OSI Approved :: MIT License
Classifier: Operating System :: OS Independent
Classifier: Programming Language :: Python :: 3
Classifier: Programming Language :: Python :: 3.10
Classifier: Programming Language :: Python :: 3.11
Classifier: Programming Language :: Python :: 3.12
Classifier: Programming Language :: Python :: 3.13
Classifier: Programming Language :: Python :: 3.14
Classifier: Programming Language :: Python :: 3.15
Classifier: Topic :: Software Development :: Libraries :: Python Modules
Project-URL: Bug Tracker, https://github.com/wow-apps/youtube-id-py/issues
Project-URL: Changelog, https://github.com/wow-apps/youtube-id-py/releases
Project-URL: Documentation, https://github.com/wow-apps/youtube-id-py#readme
Project-URL: Homepage, https://github.com/wow-apps/youtube-id-py
Project-URL: Repository, https://github.com/wow-apps/youtube-id-py
